{
  "1": {
    "name": "1. Mose",
    "language": "German",
    "translation": "Schlachter (1951)",
    "abbreviation": "schlachter",
    "textdirection": "LTR",
    "filename": "1",
    "url": "https://getbible.net/v1/schlachter/1.json",
    "sha": "a95a1aef0dbd2c496e60cccbd0689f0e8932efad",
    "id": "1"
  },
  "2": {
    "name": "2. Mose",
    "language": "German",
    "translation": "Schlachter (1951)",
    "abbreviation": "schlachter",
    "textdirection": "LTR",
    "filename": "2",
    "url": "https://getbible.net/v1/schlachter/2.json",
    "sha": "49621b4024bceed81e4d2afcf8ae19b6fc9b9fef",
    "id": "2"
  },
  "3": {
    "name": "3. Mose",
    "language": "German",
    "translation": "Schlachter (1951)",
    "abbreviation": "schlachter",
    "textdirection": "LTR",
    "filename": "3",
    "url": "https://getbible.net/v1/schlachter/3.json",
    "sha": "c75eb2485a4eeda00cedf38dd6016e62ad7b1568",
    "id": "3"
  },
  "4": {
    "name": "4. Mose",
    "language": "German",
    "translation": "Schlachter (1951)",
    "abbreviation": "schlachter",
    "textdirection": "LTR",
    "filename": "4",
    "url": "https://getbible.net/v1/schlachter/4.json",
    "sha": "5df273cf992b569b2c091808b7e939df6904e80f",
    "id": "4"
  },
  "5": {
    "name": "5. Mose",
    "language": "German",
    "translation": "Schlachter (1951)",
    "abbreviation": "schlachter",
    "textdirection": "LTR",
    "filename": "5",
    "url": "https://getbible.net/v1/schlachter/5.json",
    "sha": "adf6b730fbea91b87e50b2f461a4f2aa6c36d5e1",
    "id": "5"
  },
  "6": {
    "name": "Josua",
    "language": "German",
    "translation": "Schlachter (1951)",
    "abbreviation": "schlachter",
    "textdirection": "LTR",
    "filename": "6",
    "url": "https://getbible.net/v1/schlachter/6.json",
    "sha": "f6a7f7f0bed70c505a4837a9b7460fff53dc2175",
    "id": "6"
  },
  "7": {
    "name": "Richter",
    "language": "German",
    "translation": "Schlachter (1951)",
    "abbreviation": "schlachter",
    "textdirection": "LTR",
    "filename": "7",
    "url": "https://getbible.net/v1/schlachter/7.json",
    "sha": "41e1ee2dbae518479ee1890123305a0230a80478",
    "id": "7"
  },
  "8": {
    "name": "Rut",
    "language": "German",
    "translation": "Schlachter (1951)",
    "abbreviation": "schlachter",
    "textdirection": "LTR",
    "filename": "8",
    "url": "https://getbible.net/v1/schlachter/8.json",
    "sha": "8431de71926b8228f514c7f8d998756d70b5b464",
    "id": "8"
  },
  "9": {
    "name": "1. Samuel",
    "language": "German",
    "translation": "Schlachter (1951)",
    "abbreviation": "schlachter",
    "textdirection": "LTR",
    "filename": "9",
    "url": "https://getbible.net/v1/schlachter/9.json",
    "sha": "4c84940aa79de011ce24732bf4040f06f21221b6",
    "id": "9"
  },
  "10": {
    "name": "2. Samuel",
    "language": "German",
    "translation": "Schlachter (1951)",
    "abbreviation": "schlachter",
    "textdirection": "LTR",
    "filename": "10",
    "url": "https://getbible.net/v1/schlachter/10.json",
    "sha": "267d3945be02b89e109e7a9919a163db96def059",
    "id": "10"
  },
  "11": {
    "name": "1. Könige",
    "language": "German",
    "translation": "Schlachter (1951)",
    "abbreviation": "schlachter",
    "textdirection": "LTR",
    "filename": "11",
    "url": "https://getbible.net/v1/schlachter/11.json",
    "sha": "b5330eccc84aca795adff9bb16b8f2eafdce8b29",
    "id": "11"
  },
  "12": {
    "name": "2. Könige",
    "language": "German",
    "translation": "Schlachter (1951)",
    "abbreviation": "schlachter",
    "textdirection": "LTR",
    "filename": "12",
    "url": "https://getbible.net/v1/schlachter/12.json",
    "sha": "93ffb0888c3230d8e2d08cd0b4ef572aadb23f17",
    "id": "12"
  },
  "13": {
    "name": "1. Chronik",
    "language": "German",
    "translation": "Schlachter (1951)",
    "abbreviation": "schlachter",
    "textdirection": "LTR",
    "filename": "13",
    "url": "https://getbible.net/v1/schlachter/13.json",
    "sha": "8afbdedbee54a01fc629ca7717a11e924395204a",
    "id": "13"
  },
  "14": {
    "name": "2. Chronik",
    "language": "German",
    "translation": "Schlachter (1951)",
    "abbreviation": "schlachter",
    "textdirection": "LTR",
    "filename": "14",
    "url": "https://getbible.net/v1/schlachter/14.json",
    "sha": "03aecad8183680a49d5f8ea259f48b2b410ccd73",
    "id": "14"
  },
  "15": {
    "name": "Esra",
    "language": "German",
    "translation": "Schlachter (1951)",
    "abbreviation": "schlachter",
    "textdirection": "LTR",
    "filename": "15",
    "url": "https://getbible.net/v1/schlachter/15.json",
    "sha": "f1028e1daec8fa9ae637bd19a1901fdc27bd6d51",
    "id": "15"
  },
  "16": {
    "name": "Nehemia",
    "language": "German",
    "translation": "Schlachter (1951)",
    "abbreviation": "schlachter",
    "textdirection": "LTR",
    "filename": "16",
    "url": "https://getbible.net/v1/schlachter/16.json",
    "sha": "ae737f711af167bb01f39b0488968e5f0adbd3cb",
    "id": "16"
  },
  "17": {
    "name": "Ester",
    "language": "German",
    "translation": "Schlachter (1951)",
    "abbreviation": "schlachter",
    "textdirection": "LTR",
    "filename": "17",
    "url": "https://getbible.net/v1/schlachter/17.json",
    "sha": "b0d40e0ac551b4b879d5031545457d9634b1776f",
    "id": "17"
  },
  "18": {
    "name": "Hiob",
    "language": "German",
    "translation": "Schlachter (1951)",
    "abbreviation": "schlachter",
    "textdirection": "LTR",
    "filename": "18",
    "url": "https://getbible.net/v1/schlachter/18.json",
    "sha": "88f582965f0fdccb4698847c1ea79ca01457491c",
    "id": "18"
  },
  "19": {
    "name": "Psalmen",
    "language": "German",
    "translation": "Schlachter (1951)",
    "abbreviation": "schlachter",
    "textdirection": "LTR",
    "filename": "19",
    "url": "https://getbible.net/v1/schlachter/19.json",
    "sha": "5a0ef3e6b475bba2c871724d9bdc97775173d564",
    "id": "19"
  },
  "20": {
    "name": "Sprüche",
    "language": "German",
    "translation": "Schlachter (1951)",
    "abbreviation": "schlachter",
    "textdirection": "LTR",
    "filename": "20",
    "url": "https://getbible.net/v1/schlachter/20.json",
    "sha": "709bd02b483e36140b6b4ca1fb21dc2ed4b91391",
    "id": "20"
  },
  "21": {
    "name": "Prediger",
    "language": "German",
    "translation": "Schlachter (1951)",
    "abbreviation": "schlachter",
    "textdirection": "LTR",
    "filename": "21",
    "url": "https://getbible.net/v1/schlachter/21.json",
    "sha": "b130eea91cc43e54228ef45cc9ed53c74721dfa7",
    "id": "21"
  },
  "22": {
    "name": "Hohes Lied",
    "language": "German",
    "translation": "Schlachter (1951)",
    "abbreviation": "schlachter",
    "textdirection": "LTR",
    "filename": "22",
    "url": "https://getbible.net/v1/schlachter/22.json",
    "sha": "92139806490317bb59eb5a57dfd96352abfff6f9",
    "id": "22"
  },
  "23": {
    "name": "Jesaja",
    "language": "German",
    "translation": "Schlachter (1951)",
    "abbreviation": "schlachter",
    "textdirection": "LTR",
    "filename": "23",
    "url": "https://getbible.net/v1/schlachter/23.json",
    "sha": "3995fdea65d04fe770e663035786b904b13046a5",
    "id": "23"
  },
  "24": {
    "name": "Jeremia",
    "language": "German",
    "translation": "Schlachter (1951)",
    "abbreviation": "schlachter",
    "textdirection": "LTR",
    "filename": "24",
    "url": "https://getbible.net/v1/schlachter/24.json",
    "sha": "5584e374983d7c82006a73e4ed15076dc6d84222",
    "id": "24"
  },
  "25": {
    "name": "Klagelieder",
    "language": "German",
    "translation": "Schlachter (1951)",
    "abbreviation": "schlachter",
    "textdirection": "LTR",
    "filename": "25",
    "url": "https://getbible.net/v1/schlachter/25.json",
    "sha": "78030fe9db4748b414bcbd9f7c8e107c52225baa",
    "id": "25"
  },
  "26": {
    "name": "Hesekiel",
    "language": "German",
    "translation": "Schlachter (1951)",
    "abbreviation": "schlachter",
    "textdirection": "LTR",
    "filename": "26",
    "url": "https://getbible.net/v1/schlachter/26.json",
    "sha": "3391e9db570ae07cd935b2d256c642f6a55b7dbc",
    "id": "26"
  },
  "27": {
    "name": "Daniel",
    "language": "German",
    "translation": "Schlachter (1951)",
    "abbreviation": "schlachter",
    "textdirection": "LTR",
    "filename": "27",
    "url": "https://getbible.net/v1/schlachter/27.json",
    "sha": "b7d204b6b6805bfde4f298e2674d94d7b50e1c6a",
    "id": "27"
  },
  "28": {
    "name": "Hosea",
    "language": "German",
    "translation": "Schlachter (1951)",
    "abbreviation": "schlachter",
    "textdirection": "LTR",
    "filename": "28",
    "url": "https://getbible.net/v1/schlachter/28.json",
    "sha": "7f4b7618d9fde571fb6aab92242dba970db438a7",
    "id": "28"
  },
  "29": {
    "name": "Joel",
    "language": "German",
    "translation": "Schlachter (1951)",
    "abbreviation": "schlachter",
    "textdirection": "LTR",
    "filename": "29",
    "url": "https://getbible.net/v1/schlachter/29.json",
    "sha": "03fb6f2ae22582a0173fed6a962dad66054dadeb",
    "id": "29"
  },
  "30": {
    "name": "Amos",
    "language": "German",
    "translation": "Schlachter (1951)",
    "abbreviation": "schlachter",
    "textdirection": "LTR",
    "filename": "30",
    "url": "https://getbible.net/v1/schlachter/30.json",
    "sha": "8d9b60a06325fc2ff21b410b779419f4eb319ebc",
    "id": "30"
  },
  "31": {
    "name": "Obadja",
    "language": "German",
    "translation": "Schlachter (1951)",
    "abbreviation": "schlachter",
    "textdirection": "LTR",
    "filename": "31",
    "url": "https://getbible.net/v1/schlachter/31.json",
    "sha": "7c69ed5c79fc9eadd71f0aaf37b03e4499768ef4",
    "id": "31"
  },
  "32": {
    "name": "Jona",
    "language": "German",
    "translation": "Schlachter (1951)",
    "abbreviation": "schlachter",
    "textdirection": "LTR",
    "filename": "32",
    "url": "https://getbible.net/v1/schlachter/32.json",
    "sha": "99ade15d1b8f9ba2671d60efcf4fd9f01dcbbea1",
    "id": "32"
  },
  "33": {
    "name": "Micha",
    "language": "German",
    "translation": "Schlachter (1951)",
    "abbreviation": "schlachter",
    "textdirection": "LTR",
    "filename": "33",
    "url": "https://getbible.net/v1/schlachter/33.json",
    "sha": "867db62b2847e212ca156e38dc659e7e3f4271c4",
    "id": "33"
  },
  "34": {
    "name": "Nahum",
    "language": "German",
    "translation": "Schlachter (1951)",
    "abbreviation": "schlachter",
    "textdirection": "LTR",
    "filename": "34",
    "url": "https://getbible.net/v1/schlachter/34.json",
    "sha": "f62993bee5eab19a5280c0f71c35cd0c1de818be",
    "id": "34"
  },
  "35": {
    "name": "Habakuk",
    "language": "German",
    "translation": "Schlachter (1951)",
    "abbreviation": "schlachter",
    "textdirection": "LTR",
    "filename": "35",
    "url": "https://getbible.net/v1/schlachter/35.json",
    "sha": "0d91760bd44043a66a19a601b5056eb38d012b78",
    "id": "35"
  },
  "36": {
    "name": "Zefanja",
    "language": "German",
    "translation": "Schlachter (1951)",
    "abbreviation": "schlachter",
    "textdirection": "LTR",
    "filename": "36",
    "url": "https://getbible.net/v1/schlachter/36.json",
    "sha": "a154e378c2756cf19a960b5fbd7173a5fe12ee01",
    "id": "36"
  },
  "37": {
    "name": "Haggai",
    "language": "German",
    "translation": "Schlachter (1951)",
    "abbreviation": "schlachter",
    "textdirection": "LTR",
    "filename": "37",
    "url": "https://getbible.net/v1/schlachter/37.json",
    "sha": "87fb9898c16e1e22bd31d337e9500f4601fa7a51",
    "id": "37"
  },
  "38": {
    "name": "Sacharja",
    "language": "German",
    "translation": "Schlachter (1951)",
    "abbreviation": "schlachter",
    "textdirection": "LTR",
    "filename": "38",
    "url": "https://getbible.net/v1/schlachter/38.json",
    "sha": "32f0abc5e41efbc2b3df87a26e7f917edde5f180",
    "id": "38"
  },
  "39": {
    "name": "Maleachi",
    "language": "German",
    "translation": "Schlachter (1951)",
    "abbreviation": "schlachter",
    "textdirection": "LTR",
    "filename": "39",
    "url": "https://getbible.net/v1/schlachter/39.json",
    "sha": "bfc4a529d02637f7c0e302f08fdc42fa6e886e02",
    "id": "39"
  },
  "40": {
    "name": "Matthäus",
    "language": "German",
    "translation": "Schlachter (1951)",
    "abbreviation": "schlachter",
    "textdirection": "LTR",
    "filename": "40",
    "url": "https://getbible.net/v1/schlachter/40.json",
    "sha": "fef3326712385a93d7c020aca46fbe062e749def",
    "id": "40"
  },
  "41": {
    "name": "Markus",
    "language": "German",
    "translation": "Schlachter (1951)",
    "abbreviation": "schlachter",
    "textdirection": "LTR",
    "filename": "41",
    "url": "https://getbible.net/v1/schlachter/41.json",
    "sha": "e16f6e78ead1fdde10c75653d05fdd084b4f96c7",
    "id": "41"
  },
  "42": {
    "name": "Lukas",
    "language": "German",
    "translation": "Schlachter (1951)",
    "abbreviation": "schlachter",
    "textdirection": "LTR",
    "filename": "42",
    "url": "https://getbible.net/v1/schlachter/42.json",
    "sha": "ea04f367bcec5ba59ad3094861e9153c482f0160",
    "id": "42"
  },
  "43": {
    "name": "Johannes",
    "language": "German",
    "translation": "Schlachter (1951)",
    "abbreviation": "schlachter",
    "textdirection": "LTR",
    "filename": "43",
    "url": "https://getbible.net/v1/schlachter/43.json",
    "sha": "c8344b491a173be996280b865585d41afb0e721c",
    "id": "43"
  },
  "44": {
    "name": "Apostelgeschichte",
    "language": "German",
    "translation": "Schlachter (1951)",
    "abbreviation": "schlachter",
    "textdirection": "LTR",
    "filename": "44",
    "url": "https://getbible.net/v1/schlachter/44.json",
    "sha": "7283ee46ac3f1835eaba003e06e2fb08604838ea",
    "id": "44"
  },
  "45": {
    "name": "Römer",
    "language": "German",
    "translation": "Schlachter (1951)",
    "abbreviation": "schlachter",
    "textdirection": "LTR",
    "filename": "45",
    "url": "https://getbible.net/v1/schlachter/45.json",
    "sha": "88c5d22726147c20dc3c06ef939a297f7bd91490",
    "id": "45"
  },
  "46": {
    "name": "1. Korinther",
    "language": "German",
    "translation": "Schlachter (1951)",
    "abbreviation": "schlachter",
    "textdirection": "LTR",
    "filename": "46",
    "url": "https://getbible.net/v1/schlachter/46.json",
    "sha": "1574fab18a3a8c8703ff695e0cf3d3f85f9adb9c",
    "id": "46"
  },
  "47": {
    "name": "2. Korinther",
    "language": "German",
    "translation": "Schlachter (1951)",
    "abbreviation": "schlachter",
    "textdirection": "LTR",
    "filename": "47",
    "url": "https://getbible.net/v1/schlachter/47.json",
    "sha": "08d8ac397a930a413cb6f32141fb4608f4742e2a",
    "id": "47"
  },
  "48": {
    "name": "Galater",
    "language": "German",
    "translation": "Schlachter (1951)",
    "abbreviation": "schlachter",
    "textdirection": "LTR",
    "filename": "48",
    "url": "https://getbible.net/v1/schlachter/48.json",
    "sha": "9f6a13eff6e88fea6ba5153bcf90bbe335ba5336",
    "id": "48"
  },
  "49": {
    "name": "Epheser",
    "language": "German",
    "translation": "Schlachter (1951)",
    "abbreviation": "schlachter",
    "textdirection": "LTR",
    "filename": "49",
    "url": "https://getbible.net/v1/schlachter/49.json",
    "sha": "f9ae6ea41fe85e46249a365bfa0f4d21172ce20a",
    "id": "49"
  },
  "50": {
    "name": "Philipper",
    "language": "German",
    "translation": "Schlachter (1951)",
    "abbreviation": "schlachter",
    "textdirection": "LTR",
    "filename": "50",
    "url": "https://getbible.net/v1/schlachter/50.json",
    "sha": "d485e36631ccfca589bf8a24184bb081fa32b040",
    "id": "50"
  },
  "51": {
    "name": "Kolosser",
    "language": "German",
    "translation": "Schlachter (1951)",
    "abbreviation": "schlachter",
    "textdirection": "LTR",
    "filename": "51",
    "url": "https://getbible.net/v1/schlachter/51.json",
    "sha": "827c0507753eda3a1cd5e54a5f9bb552dc1b90a4",
    "id": "51"
  },
  "52": {
    "name": "1. Thessalonicher",
    "language": "German",
    "translation": "Schlachter (1951)",
    "abbreviation": "schlachter",
    "textdirection": "LTR",
    "filename": "52",
    "url": "https://getbible.net/v1/schlachter/52.json",
    "sha": "0315f2679509e452c5eb319ba4e6677e8c3b0ffb",
    "id": "52"
  },
  "53": {
    "name": "2. Thessalonicher",
    "language": "German",
    "translation": "Schlachter (1951)",
    "abbreviation": "schlachter",
    "textdirection": "LTR",
    "filename": "53",
    "url": "https://getbible.net/v1/schlachter/53.json",
    "sha": "ede538d6f5cf7f3feafdf69116fee6dd5a097804",
    "id": "53"
  },
  "54": {
    "name": "1. Timotheus",
    "language": "German",
    "translation": "Schlachter (1951)",
    "abbreviation": "schlachter",
    "textdirection": "LTR",
    "filename": "54",
    "url": "https://getbible.net/v1/schlachter/54.json",
    "sha": "b9344007e4417e271ce68deb681b267f511cd18c",
    "id": "54"
  },
  "55": {
    "name": "2. Timotheus",
    "language": "German",
    "translation": "Schlachter (1951)",
    "abbreviation": "schlachter",
    "textdirection": "LTR",
    "filename": "55",
    "url": "https://getbible.net/v1/schlachter/55.json",
    "sha": "b7aef2e2b1e7256513d4bfbb4db5933e213433f3",
    "id": "55"
  },
  "56": {
    "name": "Titus",
    "language": "German",
    "translation": "Schlachter (1951)",
    "abbreviation": "schlachter",
    "textdirection": "LTR",
    "filename": "56",
    "url": "https://getbible.net/v1/schlachter/56.json",
    "sha": "26506e785d4c2f4fa62c18949f913dc4bb4cb584",
    "id": "56"
  },
  "57": {
    "name": "Philemon",
    "language": "German",
    "translation": "Schlachter (1951)",
    "abbreviation": "schlachter",
    "textdirection": "LTR",
    "filename": "57",
    "url": "https://getbible.net/v1/schlachter/57.json",
    "sha": "9f13c7939ba8d1ce3820b42b60b456db263030c0",
    "id": "57"
  },
  "58": {
    "name": "Hebräer",
    "language": "German",
    "translation": "Schlachter (1951)",
    "abbreviation": "schlachter",
    "textdirection": "LTR",
    "filename": "58",
    "url": "https://getbible.net/v1/schlachter/58.json",
    "sha": "a524b9f22a44a555fe7b437b3cc025533ca9e23c",
    "id": "58"
  },
  "59": {
    "name": "Jakobus",
    "language": "German",
    "translation": "Schlachter (1951)",
    "abbreviation": "schlachter",
    "textdirection": "LTR",
    "filename": "59",
    "url": "https://getbible.net/v1/schlachter/59.json",
    "sha": "69af1ccba20dddca0b29b156cb628d9e1ef893ba",
    "id": "59"
  },
  "60": {
    "name": "1. Petrus",
    "language": "German",
    "translation": "Schlachter (1951)",
    "abbreviation": "schlachter",
    "textdirection": "LTR",
    "filename": "60",
    "url": "https://getbible.net/v1/schlachter/60.json",
    "sha": "7bf1844d75899dfa03145c6b35910059b0ce69a4",
    "id": "60"
  },
  "61": {
    "name": "2. Petrus",
    "language": "German",
    "translation": "Schlachter (1951)",
    "abbreviation": "schlachter",
    "textdirection": "LTR",
    "filename": "61",
    "url": "https://getbible.net/v1/schlachter/61.json",
    "sha": "e40168611624bdb296adae74890499441db28624",
    "id": "61"
  },
  "62": {
    "name": "1. Johannes",
    "language": "German",
    "translation": "Schlachter (1951)",
    "abbreviation": "schlachter",
    "textdirection": "LTR",
    "filename": "62",
    "url": "https://getbible.net/v1/schlachter/62.json",
    "sha": "efee5a6415aeb7abb22ef824bfc955d17fff3747",
    "id": "62"
  },
  "63": {
    "name": "2. Johannes",
    "language": "German",
    "translation": "Schlachter (1951)",
    "abbreviation": "schlachter",
    "textdirection": "LTR",
    "filename": "63",
    "url": "https://getbible.net/v1/schlachter/63.json",
    "sha": "fba81029095ebe8788f3494e4117e3a7c101bea6",
    "id": "63"
  },
  "64": {
    "name": "3. Johannes",
    "language": "German",
    "translation": "Schlachter (1951)",
    "abbreviation": "schlachter",
    "textdirection": "LTR",
    "filename": "64",
    "url": "https://getbible.net/v1/schlachter/64.json",
    "sha": "78a061c736edc06581538195c83c3bad00f8411c",
    "id": "64"
  },
  "65": {
    "name": "Judas",
    "language": "German",
    "translation": "Schlachter (1951)",
    "abbreviation": "schlachter",
    "textdirection": "LTR",
    "filename": "65",
    "url": "https://getbible.net/v1/schlachter/65.json",
    "sha": "61e1b0ff1f0cf2fbc4d17f3456bf9eae6c635d79",
    "id": "65"
  },
  "66": {
    "name": "Offenbarung",
    "language": "German",
    "translation": "Schlachter (1951)",
    "abbreviation": "schlachter",
    "textdirection": "LTR",
    "filename": "66",
    "url": "https://getbible.net/v1/schlachter/66.json",
    "sha": "ccb882c3690430a4e858e11dfcb9f682ff5fd72b",
    "id": "66"
  }
}
